{"title":"BrickLayer - 搬瓦工 认证授权模块","uid":"12fc428b925e85ceda270bf3ebacf160","slug":"projects/bricklayer/auth","date":"2022-08-14T04:28:30.000Z","updated":"2022-08-16T08:21:58.290Z","comments":true,"path":"api/articles/projects/bricklayer/auth.json","keywords":null,"cover":null,"content":"<h1 id=\"认证授权模块\"><a href=\"#认证授权模块\" class=\"headerlink\" title=\"认证授权模块\"></a>认证授权模块</h1><h2 id=\"模块需求\"><a href=\"#模块需求\" class=\"headerlink\" title=\"模块需求\"></a>模块需求</h2><ol>\n<li>签发JWT TOEKN进行认证和授权</li>\n<li>支持Gitlab, AD登录</li>\n<li>支持ABAC权限校验</li>\n</ol>\n<h3 id=\"什么是SSO\"><a href=\"#什么是SSO\" class=\"headerlink\" title=\"什么是SSO?\"></a>什么是SSO?</h3><p>利用JWTtoken完成SSO的技术要求</p>\n<p>SSO是在多个应用系统中，用户只需要登录一次就可以访问所有相互信任的应用系统。</p>\n<h3 id=\"什么OAuth2-0\"><a href=\"#什么OAuth2-0\" class=\"headerlink\" title=\"什么OAuth2.0?\"></a>什么OAuth2.0?</h3>","text":"认证授权模块模块需求 签发JWT TOEKN进行认证和授权 支持Gitlab, AD登录 支持ABAC权限校验 什么是SSO?利用JWTtoken完成SSO的技术要求 SSO是在多个应用系统中，用户只需要登录一次就可以访问所有相互信任的应用系统。 什么OAuth2.0?","link":"","photos":[],"count_time":{"symbolsCount":136,"symbolsTime":"1 mins."},"categories":[],"tags":[{"name":"SSO","slug":"SSO","count":1,"path":"api/tags/SSO.json"},{"name":"Authentication","slug":"Authentication","count":1,"path":"api/tags/Authentication.json"},{"name":"Authorization","slug":"Authorization","count":1,"path":"api/tags/Authorization.json"},{"name":"Devops","slug":"Devops","count":2,"path":"api/tags/Devops.json"},{"name":"Bricklayer","slug":"Bricklayer","count":2,"path":"api/tags/Bricklayer.json"}],"toc":"<ol class=\"toc\"><li class=\"toc-item toc-level-1\"><a class=\"toc-link\" href=\"#%E8%AE%A4%E8%AF%81%E6%8E%88%E6%9D%83%E6%A8%A1%E5%9D%97\"><span class=\"toc-text\">认证授权模块</span></a><ol class=\"toc-child\"><li class=\"toc-item toc-level-2\"><a class=\"toc-link\" href=\"#%E6%A8%A1%E5%9D%97%E9%9C%80%E6%B1%82\"><span class=\"toc-text\">模块需求</span></a><ol class=\"toc-child\"><li class=\"toc-item toc-level-3\"><a class=\"toc-link\" href=\"#%E4%BB%80%E4%B9%88%E6%98%AFSSO\"><span class=\"toc-text\">什么是SSO?</span></a></li><li class=\"toc-item toc-level-3\"><a class=\"toc-link\" href=\"#%E4%BB%80%E4%B9%88OAuth2-0\"><span class=\"toc-text\">什么OAuth2.0?</span></a></li></ol></li></ol></li></ol>","author":{"name":"Stephen Ling","slug":"blog-author","avatar":"https://img-blog.csdnimg.cn/20210313122054101.png","link":"/","description":"Think twice, code once!","socials":{"github":"","twitter":"","stackoverflow":"","wechat":"","qq":"","weibo":"","zhihu":"","csdn":"","juejin":"","customs":{}}},"mapped":true,"prev_post":{"title":"Hello World","uid":"b9663f58f18133b35bfe243f3e916a80","slug":"hello-world","date":"2022-08-16T08:21:58.290Z","updated":"2022-08-16T08:21:58.290Z","comments":true,"path":"api/articles/hello-world.json","keywords":null,"cover":null,"text":"Welcome to Hexo! This is your very first post. Check documentation for more info. If you get any problems when using Hexo, you can find the ...","link":"","photos":[],"count_time":{"symbolsCount":440,"symbolsTime":"1 mins."},"categories":[],"tags":[],"author":{"name":"Stephen Ling","slug":"blog-author","avatar":"https://img-blog.csdnimg.cn/20210313122054101.png","link":"/","description":"Think twice, code once!","socials":{"github":"","twitter":"","stackoverflow":"","wechat":"","qq":"","weibo":"","zhihu":"","csdn":"","juejin":"","customs":{}}}},"next_post":{"title":"BrickLayer - 搬瓦工","uid":"d8b335f53a173a866d08f7112a86fc25","slug":"projects/bricklayer/design","date":"2022-08-12T08:33:42.000Z","updated":"2022-08-16T08:21:58.290Z","comments":true,"path":"api/articles/projects/bricklayer/design.json","keywords":null,"cover":null,"text":"BrickLayer - 搬瓦工 设计需求 项目管理 环境管理 配置管理 CICD管理 应用监控 部署报告 测试报告 基础设施管理 kubernetes openstack baremetal 仓库管理 代码仓库 gitlab github 镜像仓库 harbor 账户管理 OA...","link":"","photos":[],"count_time":{"symbolsCount":330,"symbolsTime":"1 mins."},"categories":[],"tags":[{"name":"Devops","slug":"Devops","count":2,"path":"api/tags/Devops.json"},{"name":"Bricklayer","slug":"Bricklayer","count":2,"path":"api/tags/Bricklayer.json"}],"author":{"name":"Stephen Ling","slug":"blog-author","avatar":"https://img-blog.csdnimg.cn/20210313122054101.png","link":"/","description":"Think twice, code once!","socials":{"github":"","twitter":"","stackoverflow":"","wechat":"","qq":"","weibo":"","zhihu":"","csdn":"","juejin":"","customs":{}}}}}